{
  "project_info": {
    "project_number": "1030541858283",
    "project_id": "meme-sound-af50d",
    "storage_bucket": "meme-sound-af50d.appspot.com"
  },
  "client": [
    {
      "client_info": {
        "mobilesdk_app_id": "1:1030541858283:android:1dfd7b5251ce1f9dd635ae",
        "android_client_info": {
          "package_name": "com.sound.meme.fun.maga"
        }
      },
      "oauth_client": [],
      "api_key": [
        {
          "current_key": "AIzaSyCN8vvWZ1q0KsrGfMRBoqYIIOojK8sxvdw"
        }
      ],
      "services": {
        "appinvite_service": {
          "other_platform_oauth_client": []
        }
      }
    }
  ],
  "configuration_version": "1"
}